fw_gear_dicom_seg_to_ohif/__init__.py
fw_gear_dicom_seg_to_ohif/creator.py
fw_gear_dicom_seg_to_ohif/fw_utils.py
fw_gear_dicom_seg_to_ohif/main.py
fw_gear_dicom_seg_to_ohif/parser.py
fw_gear_dicom_seg_to_ohif/prepper.py
fw_gear_dicom_seg_to_ohif/seg_utils.py
fw_gear_dicom_seg_to_ohif-0.0.4.dist-info/LICENSE
fw_gear_dicom_seg_to_ohif-0.0.4.dist-info/METADATA
fw_gear_dicom_seg_to_ohif-0.0.4.dist-info/WHEEL
fw_gear_dicom_seg_to_ohif-0.0.4.dist-info/RECORD
