Metadata-Version: 2.1
Name: fw-gear-dicom-seg-to-ohif
Version: 0.0.4
Summary: Flywheel Gear for converting DICOM SEG ROIs to OHIF JSON
Home-page: https://gitlab.com/flywheel-io/scientific-solutions/gears/dicom-seg-to-ohif
License: MIT
Keywords: Flywheel,Gears
Author: Flywheel
Author-email: support@flywheel.io
Requires-Python: >=3.11,<4.0
Classifier: License :: OSI Approved :: MIT License
Classifier: Programming Language :: Python :: 3
Classifier: Programming Language :: Python :: 3.11
Classifier: Programming Language :: Python :: 3.12
Classifier: Topic :: Scientific/Engineering
Requires-Dist: colormath (>=3.0.0,<4.0.0)
Requires-Dist: flywheel-gear-toolkit (>=0.6.18,<0.7.0)
Requires-Dist: flywheel-sdk (>=16.19.2,<17.0.0)
Requires-Dist: fw-client (>=0.7.4,<0.8.0)
Requires-Dist: fw-file (>=3.3.2,<4.0.0)
Requires-Dist: ipykernel (>=6.29.3,<7.0.0)
Requires-Dist: scikit-image (>=0.22.0,<0.23.0)
Project-URL: Repository, https://gitlab.com/flywheel-io/scientific-solutions/gears/dicom-seg-to-ohif
